MANIFEST.in
requirements.txt
setup.py
lisa/__init__.py
lisa/plugins/__init__.py
lisa/plugins/SNCF/README.rst
lisa/plugins/SNCF/__init__.py
lisa/plugins/SNCF/sncf.json
lisa/plugins/SNCF/lang/fr/LC_MESSAGES/sncf.po
lisa/plugins/SNCF/modules/__init__.py
lisa/plugins/SNCF/modules/sncf.py
lisa/plugins/SNCF/web/__init__.py
lisa/plugins/SNCF/web/api.py
lisa/plugins/SNCF/web/models.py
lisa/plugins/SNCF/web/tests.py
lisa/plugins/SNCF/web/urls.py
lisa/plugins/SNCF/web/views.py
lisa_plugin_SNCF.egg-info/PKG-INFO
lisa_plugin_SNCF.egg-info/SOURCES.txt
lisa_plugin_SNCF.egg-info/dependency_links.txt
lisa_plugin_SNCF.egg-info/namespace_packages.txt
lisa_plugin_SNCF.egg-info/requires.txt
lisa_plugin_SNCF.egg-info/top_level.txt